aind_slurm_rest_v2/__init__.py
aind_slurm_rest_v2/api_client.py
aind_slurm_rest_v2/api_response.py
aind_slurm_rest_v2/configuration.py
aind_slurm_rest_v2/exceptions.py
aind_slurm_rest_v2/py.typed
aind_slurm_rest_v2/rest.py
aind_slurm_rest_v2/api/__init__.py
aind_slurm_rest_v2/api/slurm_api.py
aind_slurm_rest_v2/api/slurmdb_api.py
aind_slurm_rest_v2/models/__init__.py
aind_slurm_rest_v2/models/dbv0039_account_info.py
aind_slurm_rest_v2/models/dbv0039_associations_info.py
aind_slurm_rest_v2/models/dbv0039_clusters_info.py
aind_slurm_rest_v2/models/dbv0039_config_info.py
aind_slurm_rest_v2/models/dbv0039_diag.py
aind_slurm_rest_v2/models/dbv0039_error.py
aind_slurm_rest_v2/models/dbv0039_job_info.py
aind_slurm_rest_v2/models/dbv0039_meta.py
aind_slurm_rest_v2/models/dbv0039_meta_plugin.py
aind_slurm_rest_v2/models/dbv0039_meta_slurm.py
aind_slurm_rest_v2/models/dbv0039_meta_slurm_version.py
aind_slurm_rest_v2/models/dbv0039_qos_info.py
aind_slurm_rest_v2/models/dbv0039_response_associations_delete.py
aind_slurm_rest_v2/models/dbv0039_set_config.py
aind_slurm_rest_v2/models/dbv0039_tres_info.py
aind_slurm_rest_v2/models/dbv0039_tres_update.py
aind_slurm_rest_v2/models/dbv0039_update_qos.py
aind_slurm_rest_v2/models/dbv0039_update_users.py
aind_slurm_rest_v2/models/dbv0039_user_info.py
aind_slurm_rest_v2/models/dbv0039_warning.py
aind_slurm_rest_v2/models/dbv0039_wckey_info.py
aind_slurm_rest_v2/models/slurm_v0041_delete_jobs200_response.py
aind_slurm_rest_v2/models/slurm_v0041_delete_jobs200_response_status_inner.py
aind_slurm_rest_v2/models/slurm_v0041_delete_jobs200_response_status_inner_error.py
aind_slurm_rest_v2/models/slurm_v0041_delete_jobs200_response_status_inner_federation.py
aind_slurm_rest_v2/models/slurm_v0041_delete_jobs200_response_status_inner_job_id.py
aind_slurm_rest_v2/models/slurm_v0041_delete_jobs_request.py
aind_slurm_rest_v2/models/slurm_v0041_get_diag200_response.py
aind_slurm_rest_v2/models/slurm_v0041_get_diag200_response_statistics.py
aind_slurm_rest_v2-0.0.3.dist-info/licenses/LICENSE
aind_slurm_rest_v2-0.0.3.dist-info/METADATA
aind_slurm_rest_v2-0.0.3.dist-info/WHEEL
aind_slurm_rest_v2-0.0.3.dist-info/top_level.txt
aind_slurm_rest_v2-0.0.3.dist-info/RECORD
